[
  {
    "id": "c401b8b8-ac3a-4453-8002-a280602d595f",
    "status": "order",
    "vendor": "Acme Farms",
    "items": [
      {
        "sku": "APL-TRAY",
        "qty": 10,
        "price": 8.5
      }
    ],
    "dealId": null,
    "notes": "First test order",
    "createdAt": "2025-08-28T17:07:45.305Z"
  },
  {
    "id": "cdd4b7f1-6bb9-4443-bacd-648635d9a33c",
    "status": "order",
    "vendor": "Acme Farms",
    "items": [
      {
        "sku": "APL-TRAY",
        "qty": 10,
        "price": 8.5
      }
    ],
    "dealId": null,
    "notes": "First test order",
    "createdAt": "2025-08-28T17:08:18.801Z"
  }
]